mrmd_python/__init__.py
mrmd_python/__main__.py
mrmd_python/cli.py
mrmd_python/runtime_client.py
mrmd_python/runtime_daemon.py
mrmd_python/server.py
mrmd_python/subprocess_manager.py
mrmd_python/subprocess_worker.py
mrmd_python/types.py
mrmd_python/worker.py
mrmd_python-0.3.8.dist-info/METADATA
mrmd_python-0.3.8.dist-info/WHEEL
mrmd_python-0.3.8.dist-info/entry_points.txt
mrmd_python-0.3.8.dist-info/RECORD
