Metadata-Version: 2.4
Name: mrmd-python
Version: 0.3.8
Summary: Python runtime server implementing the MRMD Runtime Protocol (MRP)
Author: mrmd contributors
License: MIT
Keywords: ipython,mrmd,mrp,notebook,runtime
Classifier: Development Status :: 3 - Alpha
Classifier: Intended Audience :: Developers
Classifier: License :: OSI Approved :: MIT License
Classifier: Programming Language :: Python :: 3
Classifier: Programming Language :: Python :: 3.10
Classifier: Programming Language :: Python :: 3.11
Classifier: Programming Language :: Python :: 3.12
Classifier: Programming Language :: Python :: 3.13
Requires-Python: >=3.10
Requires-Dist: black>=25.12.0
Requires-Dist: httpx>=0.27.0
Requires-Dist: ipython>=8.0.0
Requires-Dist: jedi>=0.19.0
Requires-Dist: sse-starlette>=2.0.0
Requires-Dist: starlette>=0.40.0
Requires-Dist: uvicorn>=0.32.0
Provides-Extra: dev
Requires-Dist: httpx>=0.27.0; extra == 'dev'
Requires-Dist: pytest-asyncio>=0.24.0; extra == 'dev'
Requires-Dist: pytest>=8.0.0; extra == 'dev'
Provides-Extra: format
Requires-Dist: black>=24.0.0; extra == 'format'
